#include "instructions.h"

void (*instruction_handler[256])();

void load_instructions() {
	instruction_handler[0x32]=f_aaload;
    instruction_handler[0x53]=f_aastore;
    instruction_handler[0x01]=f_aconst_null;
    instruction_handler[0x19]=f_aload; 
    instruction_handler[0x2a]=f_aload_0;
    instruction_handler[0x2b]=f_aload_1;
    instruction_handler[0x2c]=f_aload_2;
    instruction_handler[0x2d]=f_aload_3;
    instruction_handler[0xbd]=f_anewarray; 
    instruction_handler[0xb0]=f_areturn;
    instruction_handler[0xbe]=f_arraylength;
    instruction_handler[0x3a]=f_astore; 
    instruction_handler[0x4b]=f_astore_0;
    instruction_handler[0x4c]=f_astore_1;
    instruction_handler[0x4d]=f_astore_2;
    instruction_handler[0x4e]=f_astore_3;
    instruction_handler[0xbf]=f_athrow;
    instruction_handler[0x33]=f_baload;
    instruction_handler[0x54]=f_bastore;
    instruction_handler[0x10]=f_bipush; 
    instruction_handler[0xca]=f_breakpoint;
    instruction_handler[0x34]=f_caload;
    instruction_handler[0x55]=f_castore;
    instruction_handler[0xc0]=f_checkcast; 
    instruction_handler[0x90]=f_d2f;
    instruction_handler[0x8e]=f_d2i;
    instruction_handler[0x8f]=f_d2l;
    instruction_handler[0x63]=f_dadd;
    instruction_handler[0x31]=f_daload;
    instruction_handler[0x52]=f_dastore;
    instruction_handler[0x98]=f_dcmpg;
    instruction_handler[0x97]=f_dcmpl;
    instruction_handler[0x0e]=f_dconst_0;
    instruction_handler[0x0f]=f_dconst_1;
    instruction_handler[0x6f]=f_ddiv;
    instruction_handler[0x18]=f_dload; 
    instruction_handler[0x26]=f_dload_0;
    instruction_handler[0x27]=f_dload_1;
    instruction_handler[0x28]=f_dload_2;
    instruction_handler[0x29]=f_dload_3;
    instruction_handler[0x6b]=f_dmul;
    instruction_handler[0x77]=f_dneg;
    instruction_handler[0x73]=f_drem;
    instruction_handler[0xaf]=f_dreturn;
    instruction_handler[0x39]=f_dstore; 
    instruction_handler[0x47]=f_dstore_0;
    instruction_handler[0x48]=f_dstore_1;
    instruction_handler[0x49]=f_dstore_2;
    instruction_handler[0x4a]=f_dstore_3;
    instruction_handler[0x67]=f_dsub;
    instruction_handler[0x59]=f_dup;
    instruction_handler[0x5a]=f_dup_x1;
    instruction_handler[0x5b]=f_dup_x2;
    instruction_handler[0x5c]=f_dup2;
    instruction_handler[0x5d]=f_dup2_x1;
    instruction_handler[0x5e]=f_dup2_x2;
    instruction_handler[0x8d]=f_f2d;
    instruction_handler[0x8b]=f_f2i;
    instruction_handler[0x8c]=f_f2l;
    instruction_handler[0x62]=f_fadd;
    instruction_handler[0x30]=f_faload;
    instruction_handler[0x51]=f_fastore;
    instruction_handler[0x96]=f_fcmpg;
    instruction_handler[0x95]=f_fcmpl;
    instruction_handler[0x0b]=f_fconst_0;
    instruction_handler[0x0c]=f_fconst_1;
    instruction_handler[0x0d]=f_fconst_2;
    instruction_handler[0x6e]=f_fdiv;
    instruction_handler[0x17]=f_fload; 
    instruction_handler[0x22]=f_fload_0;
    instruction_handler[0x23]=f_fload_1;
    instruction_handler[0x24]=f_fload_2;
    instruction_handler[0x25]=f_fload_3;
    instruction_handler[0x6a]=f_fmul;
    instruction_handler[0x76]=f_fneg;
    instruction_handler[0x72]=f_frem;
    instruction_handler[0xae]=f_freturn;
    instruction_handler[0x38]=f_fstore; 
    instruction_handler[0x43]=f_fstore_0;
    instruction_handler[0x44]=f_fstore_1;
    instruction_handler[0x45]=f_fstore_2;
    instruction_handler[0x46]=f_fstore_3;
    instruction_handler[0x66]=f_fsub;
    instruction_handler[0xb4]=f_getfield; 
    instruction_handler[0xb2]=f_getstatic; 
    instruction_handler[0xa7]=f_goto; 
    instruction_handler[0xc8]=f_goto_w; 
    instruction_handler[0x91]=f_i2b;
    instruction_handler[0x92]=f_i2c;
    instruction_handler[0x87]=f_i2d;
    instruction_handler[0x86]=f_i2f;
    instruction_handler[0x85]=f_i2l;
    instruction_handler[0x93]=f_i2s;
    instruction_handler[0x60]=f_iadd;
    instruction_handler[0x2e]=f_iaload;
    instruction_handler[0x7e]=f_iand;
    instruction_handler[0x4f]=f_iastore;
    instruction_handler[0x02]=f_iconst_m1;
    instruction_handler[0x03]=f_iconst_0;
    instruction_handler[0x04]=f_iconst_1;
    instruction_handler[0x05]=f_iconst_2;
    instruction_handler[0x06]=f_iconst_3;
    instruction_handler[0x07]=f_iconst_4;
    instruction_handler[0x08]=f_iconst_5;
    instruction_handler[0x6c]=f_idiv;
    instruction_handler[0xa5]=f_if_acmpeq; 
    instruction_handler[0xa6]=f_if_acmpne; 
    instruction_handler[0x9f]=f_if_icmpeq; 
    instruction_handler[0xa2]=f_if_icmpge; 
    instruction_handler[0xa3]=f_if_icmpgt; 
    instruction_handler[0xa4]=f_if_icmple; 
    instruction_handler[0xa1]=f_if_icmplt; 
    instruction_handler[0xa0]=f_if_icmpne; 
    instruction_handler[0x99]=f_ifeq; 
    instruction_handler[0x9c]=f_ifge; 
    instruction_handler[0x9d]=f_ifgt; 
    instruction_handler[0x9e]=f_ifle; 
    instruction_handler[0x9b]=f_iflt; 
    instruction_handler[0x9a]=f_ifne; 
    instruction_handler[0xc7]=f_ifnonnull; 
    instruction_handler[0xc6]=f_ifnull; 
    instruction_handler[0x84]=f_iinc; 
    instruction_handler[0x15]=f_iload; 
    instruction_handler[0x1a]=f_iload_0;
    instruction_handler[0x1b]=f_iload_1;
    instruction_handler[0x1c]=f_iload_2;
    instruction_handler[0x1d]=f_iload_3;
    instruction_handler[0xfe]=f_impdep1;
    instruction_handler[0xff]=f_impdep2;
    instruction_handler[0x68]=f_imul;
    instruction_handler[0x74]=f_ineg;
    instruction_handler[0xc1]=f_instanceof; 
    instruction_handler[0xba]=f_invokedynamic; 
    instruction_handler[0xb9]=f_invokeinterface; 
    instruction_handler[0xb7]=f_invokespecial; 
    instruction_handler[0xb8]=f_invokestatic; 
    instruction_handler[0xb6]=f_invokevirtual; 
    instruction_handler[0x80]=f_ior;
    instruction_handler[0x70]=f_irem;
    instruction_handler[0xac]=f_ireturn;
    instruction_handler[0x78]=f_ishl;
    instruction_handler[0x7a]=f_ishr;
    instruction_handler[0x36]=f_istore; 
    instruction_handler[0x3b]=f_istore_0;
    instruction_handler[0x3c]=f_istore_1;
    instruction_handler[0x3d]=f_istore_2;
    instruction_handler[0x3e]=f_istore_3;
    instruction_handler[0x64]=f_isub;
    instruction_handler[0x7c]=f_iushr;
    instruction_handler[0x82]=f_ixor;
    instruction_handler[0xa8]=f_jsr; 
    instruction_handler[0xc9]=f_jsr_w; 
    instruction_handler[0x8a]=f_l2d;
    instruction_handler[0x89]=f_l2f;
    instruction_handler[0x88]=f_l2i;
    instruction_handler[0x61]=f_ladd;
    instruction_handler[0x2f]=f_laload;
    instruction_handler[0x7f]=f_land;
    instruction_handler[0x50]=f_lastore;
    instruction_handler[0x94]=f_lcmp;
    instruction_handler[0x09]=f_lconst_0;
    instruction_handler[0x0a]=f_lconst_1;
    instruction_handler[0x12]=f_ldc; 
    instruction_handler[0x13]=f_ldc_w; 
    instruction_handler[0x14]=f_ldc2_w; 
    instruction_handler[0x6d]=f_ldiv;
    instruction_handler[0x16]=f_lload; 
    instruction_handler[0x1e]=f_lload_0;
    instruction_handler[0x1f]=f_lload_1;
    instruction_handler[0x20]=f_lload_2;
    instruction_handler[0x21]=f_lload_3;
    instruction_handler[0x69]=f_lmul;
    instruction_handler[0x75]=f_lneg;
    instruction_handler[0xab]=f_lookupswitch;
    instruction_handler[0x81]=f_lor;
    instruction_handler[0x71]=f_lrem;
    instruction_handler[0xad]=f_lreturn;
    instruction_handler[0x79]=f_lshl;
    instruction_handler[0x7b]=f_lshr;
    instruction_handler[0x37]=f_lstore; 
    instruction_handler[0x3f]=f_lstore_0;
    instruction_handler[0x40]=f_lstore_1;
    instruction_handler[0x41]=f_lstore_2;
    instruction_handler[0x42]=f_lstore_3;
    instruction_handler[0x65]=f_lsub;
    instruction_handler[0x7d]=f_lushr;
    instruction_handler[0x83]=f_lxor;
    instruction_handler[0xc2]=f_monitorenter;
    instruction_handler[0xc3]=f_monitorexit;
    instruction_handler[0xc5]=f_multianewarray; 
    instruction_handler[0xbb]=f_new; 
    instruction_handler[0xbc]=f_newarray; 
    instruction_handler[0x00]=f_nop;
    instruction_handler[0x57]=f_pop;
    instruction_handler[0x58]=f_pop2;
    instruction_handler[0xb5]=f_putfield; 
    instruction_handler[0xb3]=f_putstatic; 
    instruction_handler[0xa9]=f_ret; 
    instruction_handler[0xb1]=f_return;
    instruction_handler[0x35]=f_saload;
    instruction_handler[0x56]=f_sastore;
    instruction_handler[0x11]=f_sipush; 
    instruction_handler[0x5f]=f_swap;
    instruction_handler[0xaa]=f_tableswitch;
    instruction_handler[0xc4]=f_wide;
}
